py12306.py
py12306-0.1.0.dist-info/METADATA
py12306-0.1.0.dist-info/WHEEL
py12306-0.1.0.dist-info/entry_points.txt
py12306-0.1.0.dist-info/RECORD
